UnitTests/__init__.py
UnitTests/test_run.py
ImageUpscaler-3.0.dist-info/LICENSE
ImageUpscaler-3.0.dist-info/METADATA
ImageUpscaler-3.0.dist-info/WHEEL
ImageUpscaler-3.0.dist-info/entry_points.txt
ImageUpscaler-3.0.dist-info/top_level.txt
ImageUpscaler-3.0.dist-info/RECORD
